prusek_spheroid_segmentation/ContoursClassGUI.py
prusek_spheroid_segmentation/Funkce.py
prusek_spheroid_segmentation/GUI.py
prusek_spheroid_segmentation/GradientDescentGUI.py
prusek_spheroid_segmentation/run.py
prusek_spheroid_segmentation-0.2.dist-info/METADATA
prusek_spheroid_segmentation-0.2.dist-info/WHEEL
prusek_spheroid_segmentation-0.2.dist-info/top_level.txt
prusek_spheroid_segmentation-0.2.dist-info/RECORD
